[
  {
    "id": "b7cc3573-cc67-4e2b-b057-7fad25d3c735",
    "date": "2023-01-12T00:00:00",
    "type": "grill",
    "menu1": "PIZZA VEGGIE: Tomatensaus, mozzarella, spinazie, verse tomaat, champignons, paprika , rode ui, olijven, oregano"
  },
  {
    "id": "a1351210-c8a2-443a-a205-544e8e1e4356",
    "date": "2023-01-12T00:00:00",
    "type": "groentvdw",
    "menu1": "-Geroosterde pompoen -Gestoofde prei -Groene  kool"
  },
  {
    "id": "0c92c12b-9cf1-4005-aa11-f6301332abc7",
    "date": "2023-01-12T00:00:00",
    "type": "soep",
    "menu1": "Pompoen pastinaaksoep"
  },
  {
    "id": "cbf6e593-6b2d-456a-8ad8-db0a130473df",
    "date": "2023-01-12T00:00:00",
    "type": "veggie",
    "menu1": "Marokkaans stoofpotje met kikkererwten, zoete aardappel en couscous met nootjes"
  },
  {
    "id": "819612d6-5e19-412f-b676-044da877d3dd",
    "date": "2023-01-12T00:00:00",
    "type": "vlees",
    "menu1": "Kipfilet met pepersaus, gebakken champignons en frietjes"
  },
  {
    "id": "dfb8f550-3b08-4513-a2b2-bd2a2d754029",
    "date": "2023-01-13T00:00:00",
    "type": "groentvdw",
    "menu1": "-Geroosterde pompoen -Gestoofde prei -Groene  kool"
  },
  {
    "id": "99bb518d-a038-44c0-b6f9-0bc8d69f1668",
    "date": "2023-01-13T00:00:00",
    "type": "soep",
    "menu1": "Roomsoep Dubarry met bieslooksnippers"
  },
  {
    "id": "03ef1cdd-0c09-4fdf-a568-f36155e65602",
    "date": "2023-01-13T00:00:00",
    "type": "veggie",
    "menu1": "Gado gado burger met zoete aardappel frieten"
  },
  {
    "id": "3b60a615-9e80-4caa-bd4c-60b9e7cb3ab1",
    "date": "2023-01-13T00:00:00",
    "type": "vlees",
    "menu1": "Thai beef salade"
  },
  {
    "id": "eea41a42-524b-4cb1-b365-e47af33bc6e8",
    "date": "2023-01-14T00:00:00",
    "type": "groentvdw",
    "menu1": "-Geroosterde pompoen -Gestoofde prei -Groene  kool"
  },
  {
    "id": "634cb122-c2ff-4a6f-a855-2b33762b4e4c",
    "date": "2023-01-14T00:00:00",
    "type": "soep",
    "menu1": "Dagsoep"
  },
  {
    "id": "b78ded3b-840d-4272-9c60-a00c632b9621",
    "date": "2023-01-14T00:00:00",
    "type": "vlees",
    "menu1": "Pasta met zalm, schaaldierensaus en broccoli"
  },
  {
    "id": "50cf8330-406c-45b3-9308-6fda73c6f6f3",
    "date": "2023-01-15T00:00:00",
    "type": "groentvdw",
    "menu1": "-Geroosterde pompoen -Gestoofde prei -Groene  kool"
  },
  {
    "id": "096c7eea-2081-49ab-8de7-f6832bebff24",
    "date": "2023-01-15T00:00:00",
    "type": "soep",
    "menu1": "Dagsoep"
  },
  {
    "id": "e9918d53-d168-4845-a8bd-a45f53cd58ab",
    "date": "2023-01-15T00:00:00",
    "type": "vlees",
    "menu1": "Ossentong in Madeira met erwten op z’n Frans en kroketten"
  },
  {
    "id": "b041cf30-283c-4b92-b2c1-f7ccab109dfb",
    "date": "2023-01-16T00:00:00",
    "type": "grill",
    "menu1": "Italiaanse burger met tapenade van gegrilde groenten, rucola en mozzarella, gebakken aardappelschijven"
  },
  {
    "id": "a1548190-338c-4b3b-88a6-5a931d46db85",
    "date": "2023-01-16T00:00:00",
    "type": "groentvdw",
    "menu1": "-Gebakken schorseneren -Spinazie -Rode kool"
  },
  {
    "id": "faef3bf4-b89c-4003-9c17-12772eeb9594",
    "date": "2023-01-16T00:00:00",
    "type": "soep",
    "menu1": "Erwtensoep met croutons"
  },
  {
    "id": "e40fcb4e-0327-4c27-a9c4-e1ec46b18ed8",
    "date": "2023-01-16T00:00:00",
    "type": "veggie",
    "menu1": "Rigatoni met wintergroenten (aardpeer, raap en groene kool) en boschampignons"
  },
  {
    "id": "80d52a41-83ef-456e-af0b-6f2efecbb2e8",
    "date": "2023-01-16T00:00:00",
    "type": "vlees",
    "menu1": "Varkenslapje met broccoli gratin en gekookte aardappelen"
  },
  {
    "id": "43ab0ffc-8907-4780-bcd4-ed15899fc3e8",
    "date": "2023-01-17T00:00:00",
    "type": "grill",
    "menu1": "Pizza met champignons, artisjok en salami"
  },
  {
    "id": "226a9955-5f6b-419c-b19b-5ca610805a00",
    "date": "2023-01-17T00:00:00",
    "type": "groentvdw",
    "menu1": "-Gebakken schorseneren -Spinazie -Rode kool"
  },
  {
    "id": "bb319fee-5fca-4dd7-a048-894e0cbc9a95",
    "date": "2023-01-17T00:00:00",
    "type": "soep",
    "menu1": "Toscaanse wintersoep met savooi, knolselder, winterpeen en prei"
  },
  {
    "id": "abb7e9fe-f1b5-4e37-b9ba-c5f1f1494dd5",
    "date": "2023-01-17T00:00:00",
    "type": "veggie",
    "menu1": "Quiche met witloof, tijm, geitenkaas en honing, slaatje van veldsla"
  },
  {
    "id": "926c8f02-81a4-43c3-8381-1ce1bf1d49cf",
    "date": "2023-01-17T00:00:00",
    "type": "vlees",
    "menu1": "Koolvisfilet met Nantuasaus, oventomaatje en rijst"
  },
  {
    "id": "85596131-afa1-4398-8e31-ebbfc486b2b1",
    "date": "2023-01-18T00:00:00",
    "type": "grill",
    "menu1": "Italiaanse burger met tapenade van gegrilde groenten, rucola en mozzarella, gebakken aardappelschijven"
  },
  {
    "id": "86dfb8e3-cc39-4232-97f2-d0e9bbef6fc9",
    "date": "2023-01-18T00:00:00",
    "type": "groentvdw",
    "menu1": "-Gebakken schorseneren -Spinazie -Rode kool"
  },
  {
    "id": "a55b8539-724d-40d2-8744-53a56a651cc3",
    "date": "2023-01-18T00:00:00",
    "type": "soep",
    "menu1": "Wortel -pastinaaksoep"
  },
  {
    "id": "cf9d4f4d-e7d5-4d33-9606-36b92eec8c6f",
    "date": "2023-01-18T00:00:00",
    "type": "veggie",
    "menu1": "Ovengebakken gnocchi, butternut, champignon, ui en wokreepjes met salie en rozemarijn"
  },
  {
    "id": "7e3f0bae-178c-4cb3-95ae-bb31e4c3e139",
    "date": "2023-01-18T00:00:00",
    "type": "vlees",
    "menu1": "Lamsnavarin met couscous en oosterse groenten"
  },
  {
    "id": "2076023b-226f-47ae-80b0-e2a34c1ff5c3",
    "date": "2023-01-19T00:00:00",
    "type": "grill",
    "menu1": "Pizza met champignons, artisjok en salami"
  },
  {
    "id": "9d03cd0b-2670-4bdd-838c-5ff4665fe294",
    "date": "2023-01-19T00:00:00",
    "type": "groentvdw",
    "menu1": "-Gebakken schorseneren -Spinazie -Rode kool"
  },
  {
    "id": "cf9e34dd-42e9-47b9-8900-f746c3a3dbe1",
    "date": "2023-01-19T00:00:00",
    "type": "soep",
    "menu1": "Witloofsoep"
  },
  {
    "id": "e9ef5f1c-5f42-428c-b605-e68946dcb041",
    "date": "2023-01-19T00:00:00",
    "type": "veggie",
    "menu1": "Portobello-burger met spiegeleitje, witloofslaatje en zoete aardappelfrietjes"
  },
  {
    "id": "6e11d5cc-4ed1-4d65-8c9d-ca86dd618db3",
    "date": "2023-01-19T00:00:00",
    "type": "vlees",
    "menu1": "Steak met Choronsaus, witloofslaatje en frietjes"
  },
  {
    "id": "7d31bbff-4da1-4447-b67b-46fa5cf6357e",
    "date": "2023-01-20T00:00:00",
    "type": "groentvdw",
    "menu1": "-Gebakken schorseneren -Spinazie -Rode kool"
  },
  {
    "id": "6ee4e0a4-308b-4f77-822f-c4694e81dc8c",
    "date": "2023-01-20T00:00:00",
    "type": "soep",
    "menu1": "Preisoep"
  },
  {
    "id": "e641273a-26a0-4962-a99f-8c8e9f3fed5d",
    "date": "2023-01-20T00:00:00",
    "type": "veggie",
    "menu1": "Opgevulde paprika met Provençaalse saus en rijst"
  },
  {
    "id": "0125505c-869c-46f0-9af8-7eb87a37e974",
    "date": "2023-01-20T00:00:00",
    "type": "vlees",
    "menu1": "Pad thai met scampi"
  },
  {
    "id": "f922e9a7-75a0-47b2-b0bd-7077127a8db1",
    "date": "2023-01-21T00:00:00",
    "type": "groentvdw",
    "menu1": "-Gebakken schorseneren -Spinazie -Rode kool"
  },
  {
    "id": "e07814ac-4b6f-4610-a817-926e104d3d88",
    "date": "2023-01-21T00:00:00",
    "type": "soep",
    "menu1": "Dagsoep"
  },
  {
    "id": "412f4a2b-f0c1-4375-9d09-c99fc53211f2",
    "date": "2023-01-21T00:00:00",
    "type": "vlees",
    "menu1": "Ovenschotel met gehakt, bloemkool, broccoli en puree"
  },
  {
    "id": "5346c7f5-1c3f-498a-94c6-583afbc0e183",
    "date": "2023-01-22T00:00:00",
    "type": "groentvdw",
    "menu1": "-Gebakken schorseneren -Spinazie -Rode kool"
  },
  {
    "id": "552ed2b6-63eb-4f88-8d02-466c19b2e5b9",
    "date": "2023-01-22T00:00:00",
    "type": "soep",
    "menu1": "Dagsoep"
  },
  {
    "id": "98ea6957-3976-4a24-8864-380ef98a0d6d",
    "date": "2023-01-22T00:00:00",
    "type": "vlees",
    "menu1": "Kalkoenrollade met Portosaus, savooikool met spek en kroketten"
  },
  {
    "id": "97967a07-2e9b-4215-94cb-19c87803ba3f",
    "date": "2023-01-23T00:00:00",
    "type": "grill",
    "menu1": "Hamburger met krokante kip guacamole, cheddar, steakhouse frieten"
  },
  {
    "id": "8b78d922-7745-4b68-941b-151b42ec574c",
    "date": "2023-01-23T00:00:00",
    "type": "groentvdw",
    "menu1": "-Thijm wortelen -Witloof -Prei"
  },
  {
    "id": "cb797a7e-6b18-4e27-a83c-6479595aa79c",
    "date": "2023-01-23T00:00:00",
    "type": "soep",
    "menu1": "Champignonsoep met rode paprikablokjes"
  },
  {
    "id": "c353d36e-1b90-4a59-88a3-3fb53ca510e6",
    "date": "2023-01-23T00:00:00",
    "type": "veggie",
    "menu1": "Stamppot met pastinaak, waterkers en vegetarische balletjes"
  },
  {
    "id": "8c186a80-dfc7-434f-adb3-69200cc1c9ff",
    "date": "2023-01-23T00:00:00",
    "type": "vlees",
    "menu1": "Varkenslapje “Cross &amp; Blackwell” saus, gestoofde wortels en aardappelen"
  },
  {
    "id": "60e6bc6c-42ac-4d8c-9ebc-1873680ba03c",
    "date": "2023-01-24T00:00:00",
    "type": "grill",
    "menu1": "Pizza chorizo, paprika, ruccola en pikante olie"
  },
  {
    "id": "af1ea89d-888e-4462-a51f-847ac49a595e",
    "date": "2023-01-24T00:00:00",
    "type": "groentvdw",
    "menu1": "-Thijm wortelen -Witloof -Prei"
  },
  {
    "id": "88878688-9a63-4866-8ccf-7ed2e722d961",
    "date": "2023-01-24T00:00:00",
    "type": "soep",
    "menu1": "Seldersoep"
  },
  {
    "id": "c380332f-f72c-4b96-94d4-eacb625428bf",
    "date": "2023-01-24T00:00:00",
    "type": "veggie",
    "menu1": "Champignons Bourginon met rijst"
  },
  {
    "id": "19854ea1-1bff-4149-820d-0c8264fef5be",
    "date": "2023-01-24T00:00:00",
    "type": "vlees",
    "menu1": "Kippenpasteitje met witloofsla en frieten"
  },
  {
    "id": "f8486a90-c39e-4bfb-b46d-958a934e197c",
    "date": "2023-01-25T00:00:00",
    "type": "grill",
    "menu1": "Hamburger met krokante kip guacamole, cheddar, steakhouse frieten"
  },
  {
    "id": "969303b8-3a13-47b9-aeb1-c87928ed08ef",
    "date": "2023-01-25T00:00:00",
    "type": "groentvdw",
    "menu1": "-Thijm wortelen -Witloof -Prei"
  },
  {
    "id": "bfd86be5-86d6-4f21-b0e3-73ff6fe99ff6",
    "date": "2023-01-25T00:00:00",
    "type": "soep",
    "menu1": "Witte bonensoep"
  },
  {
    "id": "c9dcc94d-2210-4f19-b7bc-df0416edd095",
    "date": "2023-01-25T00:00:00",
    "type": "veggie",
    "menu1": "Stoofpotje van kikkererwten, zoete aardappel en pastinaak"
  },
  {
    "id": "15384a52-dc17-46a8-b683-b470a7cb884a",
    "date": "2023-01-25T00:00:00",
    "type": "vlees",
    "menu1": "Spaghetti Bolognaise"
  },
  {
    "id": "f0560f13-dd93-4f48-a9d9-f0e978cbb32f",
    "date": "2023-01-26T00:00:00",
    "type": "grill",
    "menu1": "Pizza chorizo, paprika, ruccola en pikante olie"
  },
  {
    "id": "45f2d362-40f4-4871-902f-f10478a020e5",
    "date": "2023-01-26T00:00:00",
    "type": "groentvdw",
    "menu1": "-Thijm wortelen -Witloof -Prei"
  },
  {
    "id": "2191d251-be31-4c9f-9eeb-0d90b7399f3a",
    "date": "2023-01-26T00:00:00",
    "type": "soep",
    "menu1": "Pompoensoep met curry en cocos"
  },
  {
    "id": "3be25692-1cb5-43b1-80b4-a78a9cb113e3",
    "date": "2023-01-26T00:00:00",
    "type": "veggie",
    "menu1": "Spaghetti met champignons, prei en Parmezaan schilfers"
  },
  {
    "id": "877f58e0-2c37-4a48-98f4-3ff5f9b4b88e",
    "date": "2023-01-26T00:00:00",
    "type": "vlees",
    "menu1": "Kippenbout Moambé, met roergebakken spinazie en rijst"
  }
]