[
  {
    "id": 2482,
    "date": "2022-02-16T00:00:00Z",
    "type": "soep",
    "menu1": "Tom kha kung"
  },
  {
    "id": 2483,
    "date": "2022-02-16T00:00:00Z",
    "type": "veggie",
    "menu1": "Quiche met butternut en geitenkaas met een fris rucolaslaatje"
  },
  {
    "id": 2484,
    "date": "2022-02-16T00:00:00Z",
    "type": "vlees",
    "menu1": "Ovenschotel met gehakt, zuiderse groenten en polenta"
  },
  {
    "id": 2485,
    "date": "2022-02-16T00:00:00Z",
    "type": "groentvdw",
    "menu1": "Gestoofde prei"
  },
  {
    "id": 2486,
    "date": "2022-02-17T00:00:00Z",
    "type": "soep",
    "menu1": "Dahlsoep"
  },
  {
    "id": 2487,
    "date": "2022-02-17T00:00:00Z",
    "type": "veggie",
    "menu1": "Quesadilla met avocado en zure room"
  },
  {
    "id": 2488,
    "date": "2022-02-17T00:00:00Z",
    "type": "vlees",
    "menu1": "Pompoenrisotto met gebakken bospaddenstoelen en -kabeljauw"
  },
  {
    "id": 2489,
    "date": "2022-02-17T00:00:00Z",
    "type": "groentvdw",
    "menu1": "Gestoofde prei"
  },
  {
    "id": 2490,
    "date": "2022-02-17T00:00:00Z",
    "type": "grill",
    "menu1": "Fishburger met tartaar en calamares"
  },
  {
    "id": 2491,
    "date": "2022-02-18T00:00:00Z",
    "type": "soep",
    "menu1": "Spruitensoep"
  },
  {
    "id": 2492,
    "date": "2022-02-18T00:00:00Z",
    "type": "veggie",
    "menu1": "Pesto macaroni met bladspinazie, broccoli en prei"
  },
  {
    "id": 2493,
    "date": "2022-02-18T00:00:00Z",
    "type": "vlees",
    "menu1": "Oosterse lamsballetjes met humus, komkommer- salade en pitabrood"
  },
  {
    "id": 2494,
    "date": "2022-02-18T00:00:00Z",
    "type": "groentvdw",
    "menu1": "Gestoofde prei"
  },
  {
    "id": 2495,
    "date": "2022-02-19T00:00:00Z",
    "type": "soep",
    "menu1": "Dag soep"
  },
  {
    "id": 2496,
    "date": "2022-02-19T00:00:00Z",
    "type": "vlees",
    "menu1": "Salade niçoise met gegrilde tonijn, gepocheerd ei en aardappelchips"
  },
  {
    "id": 2497,
    "date": "2022-02-19T00:00:00Z",
    "type": "groentvdw",
    "menu1": "Gestoofde prei"
  },
  {
    "id": 2498,
    "date": "2022-02-20T00:00:00Z",
    "type": "soep",
    "menu1": "Dag soep"
  },
  {
    "id": 2499,
    "date": "2022-02-20T00:00:00Z",
    "type": "vlees",
    "menu1": "Lamsepigram met gestoofde boontjes en gebakken krieltjes"
  },
  {
    "id": 2500,
    "date": "2022-02-20T00:00:00Z",
    "type": "groentvdw",
    "menu1": "Gestoofde prei"
  },
  {
    "id": 2501,
    "date": "2022-02-21T00:00:00Z",
    "type": "soep",
    "menu1": "Bouillabaisse met rouille"
  },
  {
    "id": 2502,
    "date": "2022-02-21T00:00:00Z",
    "type": "veggie",
    "menu1": "Gnocchi puttanesca"
  },
  {
    "id": 2503,
    "date": "2022-02-21T00:00:00Z",
    "type": "vlees",
    "menu1": "Braadworst met groentenhutsepot en pickles"
  },
  {
    "id": 2504,
    "date": "2022-02-21T00:00:00Z",
    "type": "groentvdw",
    "menu1": "Rode kool"
  },
  {
    "id": 2505,
    "date": "2022-02-22T00:00:00Z",
    "type": "soep",
    "menu1": "Pastinaaksoep"
  },
  {
    "id": 2506,
    "date": "2022-02-22T00:00:00Z",
    "type": "veggie",
    "menu1": "Groentenschotel stroganoff met pompoen en witte bonen met bulgur"
  },
  {
    "id": 2507,
    "date": "2022-02-22T00:00:00Z",
    "type": "vlees",
    "menu1": "Vleesbrood met witloofroom, slaatje van witloof en veldsla met kroketten"
  },
  {
    "id": 2508,
    "date": "2022-02-22T00:00:00Z",
    "type": "groentvdw",
    "menu1": "Gebakken bloemkool"
  },
  {
    "id": 2509,
    "date": "2022-02-22T00:00:00Z",
    "type": "grill",
    "menu1": "Pizza met chorizo, kip en champignon"
  },
  {
    "id": 2510,
    "date": "2022-02-23T00:00:00Z",
    "type": "soep",
    "menu1": "Rode bietensoep"
  },
  {
    "id": 2511,
    "date": "2022-02-23T00:00:00Z",
    "type": "veggie",
    "menu1": "Salade met koolrabi en rode biet met gebakken Berloumi"
  },
  {
    "id": 2512,
    "date": "2022-02-23T00:00:00Z",
    "type": "vlees",
    "menu1": "Gepaneerde pladijs met puree, huisbereide tartaar en rammenassalade"
  },
  {
    "id": 2513,
    "date": "2022-02-23T00:00:00Z",
    "type": "groentvdw",
    "menu1": "Rode kool"
  },
  {
    "id": 2514,
    "date": "2022-02-24T00:00:00Z",
    "type": "soep",
    "menu1": "Witloofsoep met witbier en korstjes"
  },
  {
    "id": 2515,
    "date": "2022-02-24T00:00:00Z",
    "type": "veggie",
    "menu1": "Biryani met muntriata (Indiaas rijstgerecht"
  },
  {
    "id": 2516,
    "date": "2022-02-24T00:00:00Z",
    "type": "vlees",
    "menu1": "Stoofpotje kip tikka masala met couscous"
  },
  {
    "id": 2517,
    "date": "2022-02-24T00:00:00Z",
    "type": "groentvdw",
    "menu1": "Gebakken bloemkool"
  },
  {
    "id": 2518,
    "date": "2022-02-24T00:00:00Z",
    "type": "grill",
    "menu1": "Pizza met chorizo, kip en champignon"
  },
  {
    "id": 2519,
    "date": "2022-02-25T00:00:00Z",
    "type": "soep",
    "menu1": "Groene seldersoep"
  },
  {
    "id": 2520,
    "date": "2022-02-25T00:00:00Z",
    "type": "veggie",
    "menu1": "Lasagne van pompoen, spinazie en ricotta"
  },
  {
    "id": 2521,
    "date": "2022-02-25T00:00:00Z",
    "type": "vlees",
    "menu1": "Tagliatelle met kalfsvlees, champignons, en spek"
  },
  {
    "id": 2522,
    "date": "2022-02-25T00:00:00Z",
    "type": "groentvdw",
    "menu1": "Rode kool"
  },
  {
    "id": 2523,
    "date": "2022-02-26T00:00:00Z",
    "type": "soep",
    "menu1": "Dag soep"
  },
  {
    "id": 2524,
    "date": "2022-02-26T00:00:00Z",
    "type": "vlees",
    "menu1": "Varkenskotelet met gestoofde prei en mosterdsaus"
  },
  {
    "id": 2525,
    "date": "2022-02-26T00:00:00Z",
    "type": "groentvdw",
    "menu1": "Rode kool of gebakken bloemkool"
  },
  {
    "id": 2526,
    "date": "2022-02-27T00:00:00Z",
    "type": "soep",
    "menu1": "Dag soep"
  },
  {
    "id": 2527,
    "date": "2022-02-27T00:00:00Z",
    "type": "vlees",
    "menu1": "Parelcouscous met rode poon, fijne mediterrane groenten en rucola"
  },
  {
    "id": 2528,
    "date": "2022-02-27T00:00:00Z",
    "type": "groentvdw",
    "menu1": "Rode kool of Gebakken bloemkool"
  },
  {
    "id": 2529,
    "date": "2022-02-28T00:00:00Z",
    "type": "soep",
    "menu1": "Juliennesoep met vermicelli"
  },
  {
    "id": 2530,
    "date": "2022-02-28T00:00:00Z",
    "type": "veggie",
    "menu1": "Bulgur met gegrilde aubergines, courgettes, vijgen en halloumi"
  },
  {
    "id": 2531,
    "date": "2022-02-28T00:00:00Z",
    "type": "vlees",
    "menu1": "Steak op Argentijnse wijze met frietjes"
  },
  {
    "id": 2532,
    "date": "2022-02-28T00:00:00Z",
    "type": "groentvdw",
    "menu1": "Italiaanse groentemengeling met pesto"
  },
  {
    "id": 2533,
    "date": "2022-03-01T00:00:00Z",
    "type": "soep",
    "menu1": "Zoete aardappelsoep"
  },
  {
    "id": 2534,
    "date": "2022-03-01T00:00:00Z",
    "type": "veggie",
    "menu1": "Wrap met falafel, hummus en sriracha-mayonaise"
  },
  {
    "id": 2535,
    "date": "2022-03-01T00:00:00Z",
    "type": "vlees",
    "menu1": "Spaghetti bolognaise"
  },
  {
    "id": 2536,
    "date": "2022-03-01T00:00:00Z",
    "type": "groentvdw",
    "menu1": "Italiaanse groenten mengeling met pesto"
  },
  {
    "id": 2537,
    "date": "2022-03-01T00:00:00Z",
    "type": "grill",
    "menu1": "Skrei met bloemkool mousseline, gebakken bloemkool, petereselie aardappelen, Noully Prat saus en grijze garnalen"
  },
  {
    "id": 2538,
    "date": "2022-03-02T00:00:00Z",
    "type": "soep",
    "menu1": "Venkelsoep met courgette"
  },
  {
    "id": 2539,
    "date": "2022-03-02T00:00:00Z",
    "type": "veggie",
    "menu1": "Spaghetti met gebakken knolselder, champignons en saus van kruidenkaas"
  },
  {
    "id": 2540,
    "date": "2022-03-02T00:00:00Z",
    "type": "vlees",
    "menu1": "Gebakken schelvis met gedroogde ham, stoemp van groene kool en mosterdsaus"
  },
  {
    "id": 2541,
    "date": "2022-03-02T00:00:00Z",
    "type": "groentvdw",
    "menu1": "Italiaanse groenten mengeling met pesto"
  }
]