<?xml version="1.0" encoding="utf-8"?><Reeks xmlns:xsi="http://www.w3.org/2001/XMLSchema-instance" xmlns:xsd="http://www.w3.org/2001/XMLSchema"><Id>210</Id><Titel>Stomp</Titel><Strips><Strip><Id>3839</Id><Nummer>1</Nummer><Titel>De spoken van Knightgrave 1</Titel><Aanwezig>true</Aanwezig><Gelezen>false</Gelezen><Afbeelding>Stomp_1_3839.jpg</Afbeelding><ReeksId>210</ReeksId></Strip><Strip><Id>3840</Id><Nummer>2</Nummer><Titel>De spoken van Knightgrave 2</Titel><Aanwezig>true</Aanwezig><Gelezen>false</Gelezen><Afbeelding>Stomp_2_3840.jpg</Afbeelding><ReeksId>210</ReeksId></Strip><Strip><Id>3841</Id><Nummer>3</Nummer><Titel>De spoken van Knightgrave 3</Titel><Aanwezig>true</Aanwezig><Gelezen>false</Gelezen><Afbeelding>Stomp_3_3841.jpg</Afbeelding><ReeksId>210</ReeksId></Strip></Strips></Reeks>