<?xml version="1.0" encoding="utf-8"?>
<Reeks xmlns:xsi="http://www.w3.org/2001/XMLSchema-instance" xmlns:xsd="http://www.w3.org/2001/XMLSchema">
  <Id>35</Id>
  <Titel>Aria</Titel>
  <Kopen>true</Kopen>
  <Strips>
    <Strip>
      <Id>1358</Id>
      <Nummer>1</Nummer>
      <Subnummer xsi:nil="true" />
      <Titel>De omzwervingen van Aria</Titel>
      <Aanwezig>true</Aanwezig>
      <Gelezen>true</Gelezen>
      <Afbeelding>Aria_1_1358.jpg</Afbeelding>
      <ReeksId>35</ReeksId>
    </Strip>
    <Strip>
      <Id>1359</Id>
      <Nummer>2</Nummer>
      <Subnummer xsi:nil="true" />
      <Titel>De berg van de heksenmeesters</Titel>
      <Aanwezig>true</Aanwezig>
      <Gelezen>true</Gelezen>
      <Afbeelding>Aria_2_1359.jpg</Afbeelding>
      <ReeksId>35</ReeksId>
    </Strip>
    <Strip>
      <Id>1360</Id>
      <Nummer>3</Nummer>
      <Subnummer xsi:nil="true" />
      <Titel>De zevende poort</Titel>
      <Aanwezig>true</Aanwezig>
      <Gelezen>true</Gelezen>
      <Afbeelding>Aria_3_1360.jpg</Afbeelding>
      <ReeksId>35</ReeksId>
    </Strip>
    <Strip>
      <Id>1361</Id>
      <Nummer>4</Nummer>
      <Subnummer xsi:nil="true" />
      <Titel>De ruiters van Aquarius</Titel>
      <Aanwezig>true</Aanwezig>
      <Gelezen>true</Gelezen>
      <Afbeelding>Aria_4_1361.jpg</Afbeelding>
      <ReeksId>35</ReeksId>
    </Strip>
    <Strip>
      <Id>1362</Id>
      <Nummer>5</Nummer>
      <Subnummer xsi:nil="true" />
      <Titel>De tranen van de godin</Titel>
      <Aanwezig>true</Aanwezig>
      <Gelezen>true</Gelezen>
      <Afbeelding>Aria_5_1362.jpg</Afbeelding>
      <ReeksId>35</ReeksId>
    </Strip>
    <Strip>
      <Id>1363</Id>
      <Nummer>6</Nummer>
      <Subnummer xsi:nil="true" />
      <Titel>De ring van de Elflings</Titel>
      <Aanwezig>true</Aanwezig>
      <Gelezen>true</Gelezen>
      <Afbeelding>Aria_6_1363.jpg</Afbeelding>
      <ReeksId>35</ReeksId>
    </Strip>
    <Strip>
      <Id>1364</Id>
      <Nummer>7</Nummer>
      <Subnummer xsi:nil="true" />
      <Titel>Het oordeel der raven</Titel>
      <Aanwezig>true</Aanwezig>
      <Gelezen>true</Gelezen>
      <Afbeelding>Aria_7_1364.jpg</Afbeelding>
      <ReeksId>35</ReeksId>
    </Strip>
    <Strip>
      <Id>1365</Id>
      <Nummer>8</Nummer>
      <Subnummer xsi:nil="true" />
      <Titel>De meridiaan van Posidonia</Titel>
      <Aanwezig>true</Aanwezig>
      <Gelezen>true</Gelezen>
      <Afbeelding>Aria_8_1365.jpg</Afbeelding>
      <ReeksId>35</ReeksId>
    </Strip>
    <Strip>
      <Id>1366</Id>
      <Nummer>9</Nummer>
      <Subnummer xsi:nil="true" />
      <Titel>Het vrouwengevecht</Titel>
      <Aanwezig>true</Aanwezig>
      <Gelezen>true</Gelezen>
      <Afbeelding>Aria_9_1366.jpg</Afbeelding>
      <ReeksId>35</ReeksId>
    </Strip>
    <Strip>
      <Id>1367</Id>
      <Nummer>10</Nummer>
      <Subnummer xsi:nil="true" />
      <Titel>Engelenoog</Titel>
      <Aanwezig>true</Aanwezig>
      <Gelezen>true</Gelezen>
      <Afbeelding>Aria_10_1367.jpg</Afbeelding>
      <ReeksId>35</ReeksId>
    </Strip>
    <Strip>
      <Id>1368</Id>
      <Nummer>11</Nummer>
      <Subnummer xsi:nil="true" />
      <Titel>De ontembaren</Titel>
      <Aanwezig>true</Aanwezig>
      <Gelezen>true</Gelezen>
      <Afbeelding>Aria_11_1368.jpg</Afbeelding>
      <ReeksId>35</ReeksId>
    </Strip>
    <Strip>
      <Id>1369</Id>
      <Nummer>12</Nummer>
      <Subnummer xsi:nil="true" />
      <Titel>Ianesch-Handra</Titel>
      <Aanwezig>true</Aanwezig>
      <Gelezen>true</Gelezen>
      <Afbeelding>Aria_12_1369.jpg</Afbeelding>
      <ReeksId>35</ReeksId>
    </Strip>
    <Strip>
      <Id>1370</Id>
      <Nummer>13</Nummer>
      <Subnummer xsi:nil="true" />
      <Titel>De stem van de profeet</Titel>
      <Aanwezig>true</Aanwezig>
      <Gelezen>true</Gelezen>
      <Afbeelding>Aria_13_1370.jpg</Afbeelding>
      <ReeksId>35</ReeksId>
    </Strip>
    <Strip>
      <Id>1371</Id>
      <Nummer>14</Nummer>
      <Subnummer xsi:nil="true" />
      <Titel>De Rover van het licht</Titel>
      <Aanwezig>true</Aanwezig>
      <Gelezen>true</Gelezen>
      <Afbeelding>Aria_14_1371.jpg</Afbeelding>
      <ReeksId>35</ReeksId>
    </Strip>
    <Strip>
      <Id>1372</Id>
      <Nummer>15</Nummer>
      <Subnummer xsi:nil="true" />
      <Titel>Venderic</Titel>
      <Aanwezig>true</Aanwezig>
      <Gelezen>true</Gelezen>
      <Afbeelding>Aria_15_1372.jpg</Afbeelding>
      <ReeksId>35</ReeksId>
    </Strip>
    <Strip>
      <Id>1373</Id>
      <Nummer>16</Nummer>
      <Subnummer xsi:nil="true" />
      <Titel>Ove</Titel>
      <Aanwezig>true</Aanwezig>
      <Gelezen>true</Gelezen>
      <Afbeelding>Aria_16_1373.jpg</Afbeelding>
      <ReeksId>35</ReeksId>
    </Strip>
    <Strip>
      <Id>1374</Id>
      <Nummer>17</Nummer>
      <Subnummer xsi:nil="true" />
      <Titel>De tuin van Satan</Titel>
      <Aanwezig>true</Aanwezig>
      <Gelezen>true</Gelezen>
      <Afbeelding>Aria_17_1374.jpg</Afbeelding>
      <ReeksId>35</ReeksId>
    </Strip>
    <Strip>
      <Id>1375</Id>
      <Nummer>18</Nummer>
      <Subnummer xsi:nil="true" />
      <Titel>Woedende Venus</Titel>
      <Aanwezig>true</Aanwezig>
      <Gelezen>true</Gelezen>
      <Afbeelding>Aria_18_1375.jpg</Afbeelding>
      <ReeksId>35</ReeksId>
    </Strip>
    <Strip>
      <Id>1376</Id>
      <Nummer>19</Nummer>
      <Subnummer xsi:nil="true" />
      <Titel>Sacristar</Titel>
      <Aanwezig>true</Aanwezig>
      <Gelezen>true</Gelezen>
      <Afbeelding>Aria_19_1376.jpg</Afbeelding>
      <ReeksId>35</ReeksId>
    </Strip>
    <Strip>
      <Id>1377</Id>
      <Nummer>20</Nummer>
      <Subnummer xsi:nil="true" />
      <Titel>Een bloem onder het hart</Titel>
      <Aanwezig>true</Aanwezig>
      <Gelezen>true</Gelezen>
      <Afbeelding>Aria_20_1377.jpg</Afbeelding>
      <ReeksId>35</ReeksId>
    </Strip>
    <Strip>
      <Id>1378</Id>
      <Nummer>21</Nummer>
      <Subnummer xsi:nil="true" />
      <Titel>De klauw van de engel</Titel>
      <Aanwezig>true</Aanwezig>
      <Gelezen>true</Gelezen>
      <Afbeelding>Aria_21_1378.jpg</Afbeelding>
      <ReeksId>35</ReeksId>
    </Strip>
    <Strip>
      <Id>1379</Id>
      <Nummer>22</Nummer>
      <Subnummer xsi:nil="true" />
      <Titel>Het spoor van de ratten</Titel>
      <Aanwezig>true</Aanwezig>
      <Gelezen>true</Gelezen>
      <Afbeelding>Aria_22_1379.jpg</Afbeelding>
      <ReeksId>35</ReeksId>
    </Strip>
    <Strip>
      <Id>1380</Id>
      <Nummer>23</Nummer>
      <Subnummer xsi:nil="true" />
      <Titel>De troetel</Titel>
      <Aanwezig>true</Aanwezig>
      <Gelezen>true</Gelezen>
      <Afbeelding>Aria_23_1380.jpg</Afbeelding>
      <ReeksId>35</ReeksId>
    </Strip>
    <Strip>
      <Id>1381</Id>
      <Nummer>24</Nummer>
      <Subnummer xsi:nil="true" />
      <Titel>De gevangen ziel</Titel>
      <Aanwezig>true</Aanwezig>
      <Gelezen>true</Gelezen>
      <Afbeelding>Aria_24_1381.jpg</Afbeelding>
      <ReeksId>35</ReeksId>
    </Strip>
    <Strip>
      <Id>1382</Id>
      <Nummer>25</Nummer>
      <Subnummer xsi:nil="true" />
      <Titel>Florina</Titel>
      <Aanwezig>true</Aanwezig>
      <Gelezen>true</Gelezen>
      <Afbeelding>Aria_25_1382.jpg</Afbeelding>
      <ReeksId>35</ReeksId>
    </Strip>
    <Strip>
      <Id>1383</Id>
      <Nummer>26</Nummer>
      <Subnummer xsi:nil="true" />
      <Titel>De tuin van Baohm</Titel>
      <Aanwezig>true</Aanwezig>
      <Gelezen>true</Gelezen>
      <Afbeelding>Aria_26_1383.jpg</Afbeelding>
      <ReeksId>35</ReeksId>
    </Strip>
    <Strip>
      <Id>1384</Id>
      <Nummer>27</Nummer>
      <Subnummer xsi:nil="true" />
      <Titel>Sterrenlied</Titel>
      <Aanwezig>true</Aanwezig>
      <Gelezen>true</Gelezen>
      <Afbeelding>Aria_27_1384.jpg</Afbeelding>
      <ReeksId>35</ReeksId>
    </Strip>
    <Strip>
      <Id>1385</Id>
      <Nummer>28</Nummer>
      <Subnummer xsi:nil="true" />
      <Titel>Het elixir van de duivel</Titel>
      <Aanwezig>true</Aanwezig>
      <Gelezen>true</Gelezen>
      <Afbeelding>Aria_28_1385.jpg</Afbeelding>
      <ReeksId>35</ReeksId>
    </Strip>
    <Strip>
      <Id>1386</Id>
      <Nummer>29</Nummer>
      <Subnummer xsi:nil="true" />
      <Titel>De maanogen</Titel>
      <Aanwezig>true</Aanwezig>
      <Gelezen>true</Gelezen>
      <Afbeelding>Aria_29_1386.jpg</Afbeelding>
      <ReeksId>35</ReeksId>
    </Strip>
    <Strip>
      <Id>1387</Id>
      <Nummer>30</Nummer>
      <Subnummer xsi:nil="true" />
      <Titel>Opnieuw geboren</Titel>
      <Aanwezig>true</Aanwezig>
      <Gelezen>true</Gelezen>
      <Afbeelding>Aria_30_1387.jpg</Afbeelding>
      <ReeksId>35</ReeksId>
    </Strip>
    <Strip>
      <Id>1388</Id>
      <Nummer>31</Nummer>
      <Subnummer xsi:nil="true" />
      <Titel>Mamaïtha</Titel>
      <Aanwezig>true</Aanwezig>
      <Gelezen>true</Gelezen>
      <Afbeelding>Aria_31_1388.jpg</Afbeelding>
      <ReeksId>35</ReeksId>
    </Strip>
    <Strip>
      <Id>1389</Id>
      <Nummer>32</Nummer>
      <Subnummer xsi:nil="true" />
      <Titel>De nieuwe duivel</Titel>
      <Aanwezig>true</Aanwezig>
      <Gelezen>true</Gelezen>
      <Afbeelding>Aria_32_1389.jpg</Afbeelding>
      <ReeksId>35</ReeksId>
    </Strip>
    <Strip>
      <Id>1390</Id>
      <Nummer>33</Nummer>
      <Subnummer xsi:nil="true" />
      <Titel>Ontsnapt aan de herinnering</Titel>
      <Aanwezig>true</Aanwezig>
      <Gelezen>true</Gelezen>
      <Afbeelding>Aria_33_1390.jpg</Afbeelding>
      <ReeksId>35</ReeksId>
    </Strip>
    <Strip>
      <Id>1391</Id>
      <Nummer>34</Nummer>
      <Subnummer xsi:nil="true" />
      <Titel>De krochten van de dood</Titel>
      <Aanwezig>true</Aanwezig>
      <Gelezen>true</Gelezen>
      <Afbeelding>Aria_34_1391.jpg</Afbeelding>
      <ReeksId>35</ReeksId>
    </Strip>
    <Strip>
      <Id>1392</Id>
      <Nummer>35</Nummer>
      <Subnummer xsi:nil="true" />
      <Titel>De feniks verrijst</Titel>
      <Aanwezig>true</Aanwezig>
      <Gelezen>true</Gelezen>
      <Afbeelding>Aria_35_1392.jpg</Afbeelding>
      <ReeksId>35</ReeksId>
    </Strip>
    <Strip>
      <Id>1393</Id>
      <Nummer>36</Nummer>
      <Subnummer xsi:nil="true" />
      <Titel>Het bergpad</Titel>
      <Aanwezig>true</Aanwezig>
      <Gelezen>true</Gelezen>
      <Afbeelding>Aria_36_1393.jpg</Afbeelding>
      <ReeksId>35</ReeksId>
    </Strip>
    <Strip>
      <Id>1394</Id>
      <Nummer>37</Nummer>
      <Subnummer xsi:nil="true" />
      <Titel>Laat de beschuldigde zwijgen</Titel>
      <Aanwezig>true</Aanwezig>
      <Gelezen>false</Gelezen>
      <Afbeelding>Aria_37_1394.jpg</Afbeelding>
      <ReeksId>35</ReeksId>
    </Strip>
    <Strip>
      <Id>1395</Id>
      <Nummer>38</Nummer>
      <Subnummer xsi:nil="true" />
      <Titel>De troon van de duivel</Titel>
      <Aanwezig>true</Aanwezig>
      <Gelezen>false</Gelezen>
      <Afbeelding>Aria_38_1395.jpg</Afbeelding>
      <ReeksId>35</ReeksId>
    </Strip>
    <Strip>
      <Id>1396</Id>
      <Nummer>39</Nummer>
      <Subnummer xsi:nil="true" />
      <Titel>Het heilzame vuur</Titel>
      <Aanwezig>true</Aanwezig>
      <Gelezen>false</Gelezen>
      <Afbeelding>Aria_39_1396.jpg</Afbeelding>
      <ReeksId>35</ReeksId>
    </Strip>
    <Strip>
      <Id>1397</Id>
      <Nummer>40</Nummer>
      <Subnummer xsi:nil="true" />
      <Titel>Reisverslag</Titel>
      <Aanwezig>true</Aanwezig>
      <Gelezen>false</Gelezen>
      <Afbeelding>Aria_40_1397.jpg</Afbeelding>
      <ReeksId>35</ReeksId>
    </Strip>
  </Strips>
</Reeks>