<?xml version="1.0" encoding="utf-8"?>
<Reeks xmlns:xsi="http://www.w3.org/2001/XMLSchema-instance" xmlns:xsd="http://www.w3.org/2001/XMLSchema">
  <Id>28</Id>
  <Titel>Amoras</Titel>
  <Kopen>true</Kopen>
  <Strips>
    <Strip>
      <Id>1289</Id>
      <Nummer>1</Nummer>
      <Subnummer xsi:nil="true" />
      <Titel>Suske</Titel>
      <Aanwezig>true</Aanwezig>
      <Gelezen>true</Gelezen>
      <Afbeelding>Amoras_1_1289.jpg</Afbeelding>
      <ReeksId>28</ReeksId>
    </Strip>
    <Strip>
      <Id>1290</Id>
      <Nummer>2</Nummer>
      <Subnummer xsi:nil="true" />
      <Titel>Jérusalem</Titel>
      <Aanwezig>true</Aanwezig>
      <Gelezen>true</Gelezen>
      <Afbeelding>Amoras_2_1290.jpg</Afbeelding>
      <ReeksId>28</ReeksId>
    </Strip>
    <Strip>
      <Id>1291</Id>
      <Nummer>3</Nummer>
      <Subnummer xsi:nil="true" />
      <Titel>Krimson</Titel>
      <Aanwezig>true</Aanwezig>
      <Gelezen>true</Gelezen>
      <Afbeelding>Amoras_3_1291.jpg</Afbeelding>
      <ReeksId>28</ReeksId>
    </Strip>
    <Strip>
      <Id>1292</Id>
      <Nummer>4</Nummer>
      <Subnummer xsi:nil="true" />
      <Titel>Lambik</Titel>
      <Aanwezig>true</Aanwezig>
      <Gelezen>true</Gelezen>
      <Afbeelding>Amoras_4_1292.jpg</Afbeelding>
      <ReeksId>28</ReeksId>
    </Strip>
    <Strip>
      <Id>1293</Id>
      <Nummer>5</Nummer>
      <Subnummer xsi:nil="true" />
      <Titel>Wiske</Titel>
      <Aanwezig>true</Aanwezig>
      <Gelezen>true</Gelezen>
      <Afbeelding>Amoras_5_1293.jpg</Afbeelding>
      <ReeksId>28</ReeksId>
    </Strip>
    <Strip>
      <Id>1294</Id>
      <Nummer>6</Nummer>
      <Subnummer xsi:nil="true" />
      <Titel>Barabas</Titel>
      <Aanwezig>true</Aanwezig>
      <Gelezen>true</Gelezen>
      <Afbeelding>Amoras_6_1294.jpg</Afbeelding>
      <ReeksId>28</ReeksId>
    </Strip>
  </Strips>
</Reeks>