<Reeks><ID>193</ID><Titel>Cyclus van Cyann, De</Titel><Strip><ID>2565</ID><Nummer>1</Nummer><Titel>De brOn en de sOnde</Titel><Aanwezig>1</Aanwezig><Gelezen>0</Gelezen></Strip><Strip><ID>2566</ID><Nummer>2</Nummer><Titel>Zes seizoenen op IlO</Titel><Aanwezig>1</Aanwezig><Gelezen>0</Gelezen></Strip><Strip><ID>2567</ID><Nummer>3</Nummer><Titel>Aïeïa van Aldaal</Titel><Aanwezig>1</Aanwezig><Gelezen>0</Gelezen></Strip><Strip><ID>2568</ID><Nummer>4</Nummer><Titel>De kleuren van Marcade</Titel><Aanwezig>1</Aanwezig><Gelezen>0</Gelezen></Strip><Strip><ID>2569</ID><Nummer>5</Nummer><Titel>De gangen van de tussentijd</Titel><Aanwezig>1</Aanwezig><Gelezen>0</Gelezen></Strip><Strip><ID>2778</ID><Nummer>6</Nummer><Titel>De zoete dageraad van Aldalarann</Titel><Aanwezig>1</Aanwezig><Gelezen>0</Gelezen></Strip></Reeks>