<Reeks><ID>155</ID><Titel>Charly</Titel><Strip><ID>2295</ID><Nummer>1</Nummer><Titel>Duivels speelgoed</Titel><Aanwezig>1</Aanwezig><Gelezen>1</Gelezen></Strip><Strip><ID>2296</ID><Nummer>2</Nummer><Titel>Het verloren eiland</Titel><Aanwezig>1</Aanwezig><Gelezen>1</Gelezen></Strip><Strip><ID>2297</ID><Nummer>3</Nummer><Titel>Dreigende bliksem</Titel><Aanwezig>1</Aanwezig><Gelezen>1</Gelezen></Strip><Strip><ID>2298</ID><Nummer>4</Nummer><Titel>De valstrik</Titel><Aanwezig>1</Aanwezig><Gelezen>1</Gelezen></Strip><Strip><ID>2299</ID><Nummer>5</Nummer><Titel>Nachtmerries</Titel><Aanwezig>1</Aanwezig><Gelezen>0</Gelezen></Strip><Strip><ID>2300</ID><Nummer>6</Nummer><Titel>De moordenaar</Titel><Aanwezig>1</Aanwezig><Gelezen>0</Gelezen></Strip><Strip><ID>2301</ID><Nummer>7</Nummer><Titel>De onschuld</Titel><Aanwezig>1</Aanwezig><Gelezen>0</Gelezen></Strip><Strip><ID>2302</ID><Nummer>8</Nummer><Titel>Vuurogen</Titel><Aanwezig>1</Aanwezig><Gelezen>0</Gelezen></Strip><Strip><ID>2303</ID><Nummer>9</Nummer><Titel>Berichten uit vervlogen tijden</Titel><Aanwezig>1</Aanwezig><Gelezen>0</Gelezen></Strip><Strip><ID>2304</ID><Nummer>10</Nummer><Titel>Engel</Titel><Aanwezig>1</Aanwezig><Gelezen>0</Gelezen></Strip><Strip><ID>2305</ID><Nummer>11</Nummer><Titel>Een eeuwig leven</Titel><Aanwezig>1</Aanwezig><Gelezen>0</Gelezen></Strip><Strip><ID>2306</ID><Nummer>12</Nummer><Titel>Moordenaar!</Titel><Aanwezig>1</Aanwezig><Gelezen>0</Gelezen></Strip><Strip><ID>2307</ID><Nummer>13</Nummer><Titel>Een hel op aarde</Titel><Aanwezig>1</Aanwezig><Gelezen>0</Gelezen></Strip></Reeks>