<Reeks><ID>61</ID><Titel>Rubine</Titel><Strip><ID>1438</ID><Nummer>1</Nummer><Titel>Het verstoorde geheugen</Titel><Aanwezig>1</Aanwezig><Gelezen>1</Gelezen></Strip><Strip><ID>1439</ID><Nummer>2</Nummer><Titel>Uitzicht op straat</Titel><Aanwezig>1</Aanwezig><Gelezen>1</Gelezen></Strip><Strip><ID>1440</ID><Nummer>3</Nummer><Titel>De tweede getuige</Titel><Aanwezig>1</Aanwezig><Gelezen>1</Gelezen></Strip><Strip><ID>1441</ID><Nummer>4</Nummer><Titel>Serial killer</Titel><Aanwezig>1</Aanwezig><Gelezen>1</Gelezen></Strip><Strip><ID>1442</ID><Nummer>5</Nummer><Titel>Vedwenen op Halloween</Titel><Aanwezig>1</Aanwezig><Gelezen>1</Gelezen></Strip><Strip><ID>1443</ID><Nummer>6</Nummer><Titel>America</Titel><Aanwezig>1</Aanwezig><Gelezen>1</Gelezen></Strip><Strip><ID>1444</ID><Nummer>7</Nummer><Titel>Werkvakantie</Titel><Aanwezig>1</Aanwezig><Gelezen>1</Gelezen></Strip><Strip><ID>1445</ID><Nummer>8</Nummer><Titel>96 Uur</Titel><Aanwezig>1</Aanwezig><Gelezen>1</Gelezen></Strip><Strip><ID>1838</ID><Nummer>9</Nummer><Titel>Modelstad</Titel><Aanwezig>1</Aanwezig><Gelezen>1</Gelezen></Strip><Strip><ID>2015</ID><Nummer>10</Nummer><Titel>Zwarte reeks</Titel><Aanwezig>1</Aanwezig><Gelezen>1</Gelezen></Strip><Strip><ID>2227</ID><Nummer>11</Nummer><Titel>Klassenfoto</Titel><Aanwezig>1</Aanwezig><Gelezen>1</Gelezen></Strip><Strip><ID>2324</ID><Nummer>12</Nummer><Titel>Lake Wakanala</Titel><Aanwezig>1</Aanwezig><Gelezen>0</Gelezen></Strip><Strip><ID>2380</ID><Nummer>13</Nummer><Titel>De kwetsbare erfgenaam</Titel><Aanwezig>1</Aanwezig><Gelezen>1</Gelezen></Strip></Reeks>