<Reeks><ID>42</ID><Titel>Storm</Titel><Strip><ID>1898</ID><Nummer>0</Nummer><Titel>Commandant Grek, gevangenen van de tijd</Titel><Aanwezig>1</Aanwezig><Gelezen>1</Gelezen></Strip><Strip><ID>3336</ID><Nummer>0</Nummer><Titel>Hommages</Titel><Aanwezig>1</Aanwezig><Gelezen>0</Gelezen></Strip><Strip><ID>1148</ID><Nummer>1</Nummer><Titel>De diepe wereld</Titel><Aanwezig>1</Aanwezig><Gelezen>1</Gelezen></Strip><Strip><ID>1149</ID><Nummer>2</Nummer><Titel>De laatste vechter</Titel><Aanwezig>1</Aanwezig><Gelezen>1</Gelezen></Strip><Strip><ID>1150</ID><Nummer>3</Nummer><Titel>Het volk van de woestijn</Titel><Aanwezig>1</Aanwezig><Gelezen>1</Gelezen></Strip><Strip><ID>1151</ID><Nummer>4</Nummer><Titel>De groene hel</Titel><Aanwezig>1</Aanwezig><Gelezen>1</Gelezen></Strip><Strip><ID>1152</ID><Nummer>5</Nummer><Titel>De strijd om de aarde</Titel><Aanwezig>1</Aanwezig><Gelezen>1</Gelezen></Strip><Strip><ID>1153</ID><Nummer>6</Nummer><Titel>Het geheim van de Nitronstralen</Titel><Aanwezig>1</Aanwezig><Gelezen>1</Gelezen></Strip><Strip><ID>1154</ID><Nummer>7</Nummer><Titel>De legende van Yggdrasil</Titel><Aanwezig>1</Aanwezig><Gelezen>1</Gelezen></Strip><Strip><ID>1155</ID><Nummer>8</Nummer><Titel>Stad der verdoemden</Titel><Aanwezig>1</Aanwezig><Gelezen>1</Gelezen></Strip><Strip><ID>1156</ID><Nummer>9</Nummer><Titel>De sluimerende dood</Titel><Aanwezig>1</Aanwezig><Gelezen>1</Gelezen></Strip><Strip><ID>1157</ID><Nummer>10</Nummer><Titel>De piraten van Pandarve</Titel><Aanwezig>1</Aanwezig><Gelezen>1</Gelezen></Strip><Strip><ID>1158</ID><Nummer>11</Nummer><Titel>Het doolhof van de dood</Titel><Aanwezig>1</Aanwezig><Gelezen>1</Gelezen></Strip><Strip><ID>1159</ID><Nummer>12</Nummer><Titel>De zeven van Aromater</Titel><Aanwezig>1</Aanwezig><Gelezen>1</Gelezen></Strip><Strip><ID>1160</ID><Nummer>13</Nummer><Titel>De doder van Eriban</Titel><Aanwezig>1</Aanwezig><Gelezen>1</Gelezen></Strip><Strip><ID>1161</ID><Nummer>14</Nummer><Titel>De honden van Marduk</Titel><Aanwezig>1</Aanwezig><Gelezen>1</Gelezen></Strip><Strip><ID>1162</ID><Nummer>15</Nummer><Titel>De levende planeet</Titel><Aanwezig>1</Aanwezig><Gelezen>1</Gelezen></Strip><Strip><ID>1163</ID><Nummer>16</Nummer><Titel>Vandaahl de verderver</Titel><Aanwezig>1</Aanwezig><Gelezen>1</Gelezen></Strip><Strip><ID>1164</ID><Nummer>17</Nummer><Titel>De wentelwereld</Titel><Aanwezig>1</Aanwezig><Gelezen>1</Gelezen></Strip><Strip><ID>1165</ID><Nummer>18</Nummer><Titel>De robots van Danderzei</Titel><Aanwezig>1</Aanwezig><Gelezen>1</Gelezen></Strip><Strip><ID>1166</ID><Nummer>19</Nummer><Titel>De terugkeer van de Rode Prins</Titel><Aanwezig>1</Aanwezig><Gelezen>1</Gelezen></Strip><Strip><ID>1167</ID><Nummer>20</Nummer><Titel>De Von Neumann-Machine</Titel><Aanwezig>1</Aanwezig><Gelezen>1</Gelezen></Strip><Strip><ID>1168</ID><Nummer>21</Nummer><Titel>De Genesis-Formule</Titel><Aanwezig>1</Aanwezig><Gelezen>1</Gelezen></Strip><Strip><ID>1899</ID><Nummer>22</Nummer><Titel>De armageddon reiziger</Titel><Aanwezig>1</Aanwezig><Gelezen>1</Gelezen></Strip><Strip><ID>2138</ID><Nummer>23</Nummer><Titel>De navel van de dubbele god</Titel><Aanwezig>1</Aanwezig><Gelezen>1</Gelezen></Strip><Strip><ID>2169</ID><Nummer>24</Nummer><Titel>De bronnen van Marduk</Titel><Aanwezig>1</Aanwezig><Gelezen>1</Gelezen></Strip><Strip><ID>2327</ID><Nummer>25</Nummer><Titel>Het rode spoor</Titel><Aanwezig>1</Aanwezig><Gelezen>0</Gelezen></Strip><Strip><ID>2385</ID><Nummer>26</Nummer><Titel>De muiters van Anker</Titel><Aanwezig>1</Aanwezig><Gelezen>0</Gelezen></Strip><Strip><ID>2537</ID><Nummer>27</Nummer><Titel>De wisselwachters</Titel><Aanwezig>1</Aanwezig><Gelezen>0</Gelezen></Strip><Strip><ID>2684</ID><Nummer>28</Nummer><Titel>De race van Opaal</Titel><Aanwezig>1</Aanwezig><Gelezen>0</Gelezen></Strip><Strip><ID>2812</ID><Nummer>29</Nummer><Titel>Het koraal van Kesmee</Titel><Aanwezig>1</Aanwezig><Gelezen>0</Gelezen></Strip><Strip><ID>3107</ID><Nummer>30</Nummer><Titel>De beul van Torkien</Titel><Aanwezig>1</Aanwezig><Gelezen>0</Gelezen></Strip><Strip><ID>3250</ID><Nummer>31</Nummer><Titel>Het gesticht van Krijs</Titel><Aanwezig>1</Aanwezig><Gelezen>0</Gelezen></Strip><Strip><ID>3292</ID><Nummer>32</Nummer><Titel>Het offer van Narvatica</Titel><Aanwezig>1</Aanwezig><Gelezen>0</Gelezen></Strip><Strip><ID>3402</ID><Nummer>33</Nummer><Titel>De archivaris van het licht</Titel><Aanwezig>0</Aanwezig><Gelezen>0</Gelezen></Strip></Reeks>