<?xml version="1.0" encoding="utf-8"?>
<Reeks xmlns:xsi="http://www.w3.org/2001/XMLSchema-instance" xmlns:xsd="http://www.w3.org/2001/XMLSchema">
  <Id>156</Id>
  <Titel>Mr. Kweeniewa en geniale Olivier</Titel>
  <Kopen>false</Kopen>
  <Strips>
    <Strip>
      <Id>2818</Id>
      <Nummer>1</Nummer>
      <Subnummer xsi:nil="true" />
      <Titel>De dolle school</Titel>
      <Aanwezig>false</Aanwezig>
      <Gelezen>false</Gelezen>
      <Afbeelding>MrKweeniewaengenialeOlivier_1_2818.jpg</Afbeelding>
      <ReeksId>156</ReeksId>
    </Strip>
    <Strip>
      <Id>2819</Id>
      <Nummer>2</Nummer>
      <Subnummer xsi:nil="true" />
      <Titel>Het genie en zijn generatie</Titel>
      <Aanwezig>false</Aanwezig>
      <Gelezen>false</Gelezen>
      <Afbeelding>MrKweeniewaengenialeOlivier_2_2819.jpg</Afbeelding>
      <ReeksId>156</ReeksId>
    </Strip>
    <Strip>
      <Id>2820</Id>
      <Nummer>3</Nummer>
      <Subnummer xsi:nil="true" />
      <Titel>Genie, Vidi, Vici!</Titel>
      <Aanwezig>false</Aanwezig>
      <Gelezen>false</Gelezen>
      <Afbeelding>MrKweeniewaengenialeOlivier_3_2820.jpg</Afbeelding>
      <ReeksId>156</ReeksId>
    </Strip>
    <Strip>
      <Id>2821</Id>
      <Nummer>4</Nummer>
      <Subnummer xsi:nil="true" />
      <Titel>Gedwarsboomd, gul genie...</Titel>
      <Aanwezig>false</Aanwezig>
      <Gelezen>false</Gelezen>
      <Afbeelding>MrKweeniewaengenialeOlivier_4_2821.jpg</Afbeelding>
      <ReeksId>156</ReeksId>
    </Strip>
    <Strip>
      <Id>2822</Id>
      <Nummer>5</Nummer>
      <Subnummer xsi:nil="true" />
      <Titel>Het genie gedijt goed!</Titel>
      <Aanwezig>false</Aanwezig>
      <Gelezen>false</Gelezen>
      <Afbeelding>MrKweeniewaengenialeOlivier_5_2822.jpg</Afbeelding>
      <ReeksId>156</ReeksId>
    </Strip>
    <Strip>
      <Id>2823</Id>
      <Nummer>6</Nummer>
      <Subnummer xsi:nil="true" />
      <Titel>Een ingenieus ingebnieur</Titel>
      <Aanwezig>false</Aanwezig>
      <Gelezen>false</Gelezen>
      <Afbeelding>MrKweeniewaengenialeOlivier_6_2823.jpg</Afbeelding>
      <ReeksId>156</ReeksId>
    </Strip>
    <Strip>
      <Id>2824</Id>
      <Nummer>7</Nummer>
      <Subnummer xsi:nil="true" />
      <Titel>Verleden voor de klas</Titel>
      <Aanwezig>false</Aanwezig>
      <Gelezen>false</Gelezen>
      <Afbeelding>MrKweeniewaengenialeOlivier_7_2824.jpg</Afbeelding>
      <ReeksId>156</ReeksId>
    </Strip>
    <Strip>
      <Id>2825</Id>
      <Nummer>8</Nummer>
      <Subnummer xsi:nil="true" />
      <Titel>Elektronen, moleculen en huiswerk</Titel>
      <Aanwezig>false</Aanwezig>
      <Gelezen>false</Gelezen>
      <Afbeelding>MrKweeniewaengenialeOlivier_8_2825.jpg</Afbeelding>
      <ReeksId>156</ReeksId>
    </Strip>
    <Strip>
      <Id>2826</Id>
      <Nummer>9</Nummer>
      <Subnummer xsi:nil="true" />
      <Titel>Elektronen en Edelzonen</Titel>
      <Aanwezig>false</Aanwezig>
      <Gelezen>false</Gelezen>
      <Afbeelding>MrKweeniewaengenialeOlivier_9_2826.jpg</Afbeelding>
      <ReeksId>156</ReeksId>
    </Strip>
    <Strip>
      <Id>2827</Id>
      <Nummer>10</Nummer>
      <Subnummer xsi:nil="true" />
      <Titel>Een genietend genie</Titel>
      <Aanwezig>false</Aanwezig>
      <Gelezen>false</Gelezen>
      <Afbeelding>MrKweeniewaengenialeOlivier_10_2827.jpg</Afbeelding>
      <ReeksId>156</ReeksId>
    </Strip>
    <Strip>
      <Id>2828</Id>
      <Nummer>11</Nummer>
      <Subnummer xsi:nil="true" />
      <Titel>Geniale grappen en grollen</Titel>
      <Aanwezig>false</Aanwezig>
      <Gelezen>false</Gelezen>
      <Afbeelding>MrKweeniewaengenialeOlivier_11_2828.jpg</Afbeelding>
      <ReeksId>156</ReeksId>
    </Strip>
    <Strip>
      <Id>2829</Id>
      <Nummer>12</Nummer>
      <Subnummer xsi:nil="true" />
      <Titel>'n Vrijgevig genie</Titel>
      <Aanwezig>false</Aanwezig>
      <Gelezen>false</Gelezen>
      <Afbeelding>MrKweeniewaengenialeOlivier_12_2829.jpg</Afbeelding>
      <ReeksId>156</ReeksId>
    </Strip>
    <Strip>
      <Id>2830</Id>
      <Nummer>13</Nummer>
      <Subnummer xsi:nil="true" />
      <Titel>Een genieperig genie</Titel>
      <Aanwezig>false</Aanwezig>
      <Gelezen>false</Gelezen>
      <Afbeelding>MrKweeniewaengenialeOlivier_13_2830.jpg</Afbeelding>
      <ReeksId>156</ReeksId>
    </Strip>
    <Strip>
      <Id>2831</Id>
      <Nummer>14</Nummer>
      <Subnummer xsi:nil="true" />
      <Titel>Een geducht genie</Titel>
      <Aanwezig>false</Aanwezig>
      <Gelezen>false</Gelezen>
      <Afbeelding>MrKweeniewaengenialeOlivier_14_2831.jpg</Afbeelding>
      <ReeksId>156</ReeksId>
    </Strip>
    <Strip>
      <Id>2832</Id>
      <Nummer>15</Nummer>
      <Subnummer xsi:nil="true" />
      <Titel>Genie in Hi-Fi</Titel>
      <Aanwezig>true</Aanwezig>
      <Gelezen>true</Gelezen>
      <Afbeelding>MrKweeniewaengenialeOlivier_15_2832.jpg</Afbeelding>
      <ReeksId>156</ReeksId>
    </Strip>
    <Strip>
      <Id>2833</Id>
      <Nummer>16</Nummer>
      <Subnummer xsi:nil="true" />
      <Titel>Een goedlachs genie</Titel>
      <Aanwezig>false</Aanwezig>
      <Gelezen>false</Gelezen>
      <Afbeelding>MrKweeniewaengenialeOlivier_16_2833.jpg</Afbeelding>
      <ReeksId>156</ReeksId>
    </Strip>
    <Strip>
      <Id>2834</Id>
      <Nummer>17</Nummer>
      <Subnummer xsi:nil="true" />
      <Titel>Meervoudig genie</Titel>
      <Aanwezig>false</Aanwezig>
      <Gelezen>false</Gelezen>
      <Afbeelding>MrKweeniewaengenialeOlivier_17_2834.jpg</Afbeelding>
      <ReeksId>156</ReeksId>
    </Strip>
  </Strips>
</Reeks>