<Reeks><ID>181</ID><Titel>Empire USA</Titel><Strip><ID>2502</ID><Nummer>1</Nummer><Titel/><Aanwezig>1</Aanwezig><Gelezen>0</Gelezen></Strip><Strip><ID>2503</ID><Nummer>2</Nummer><Titel/><Aanwezig>1</Aanwezig><Gelezen>0</Gelezen></Strip><Strip><ID>2504</ID><Nummer>3</Nummer><Titel/><Aanwezig>1</Aanwezig><Gelezen>0</Gelezen></Strip><Strip><ID>2505</ID><Nummer>4</Nummer><Titel/><Aanwezig>1</Aanwezig><Gelezen>0</Gelezen></Strip><Strip><ID>2506</ID><Nummer>5</Nummer><Titel/><Aanwezig>1</Aanwezig><Gelezen>0</Gelezen></Strip><Strip><ID>2507</ID><Nummer>6</Nummer><Titel/><Aanwezig>1</Aanwezig><Gelezen>0</Gelezen></Strip></Reeks>