<Reeks><ID>78</ID><Titel>Isabelle Avondrood, De fantastische avonturen van</Titel><Strip><ID>1547</ID><Nummer>1</Nummer><Titel>Isabelle en het monster</Titel><Aanwezig>1</Aanwezig><Gelezen>1</Gelezen></Strip><Strip><ID>1548</ID><Nummer>2</Nummer><Titel>De demon van de eiffeltoren</Titel><Aanwezig>1</Aanwezig><Gelezen>1</Gelezen></Strip><Strip><ID>1549</ID><Nummer>3</Nummer><Titel>De waanzinnige geleerde</Titel><Aanwezig>1</Aanwezig><Gelezen>1</Gelezen></Strip><Strip><ID>1550</ID><Nummer>4</Nummer><Titel>Maanzieke mummies</Titel><Aanwezig>1</Aanwezig><Gelezen>1</Gelezen></Strip><Strip><ID>1551</ID><Nummer>5</Nummer><Titel>Het geheim van de salamander</Titel><Aanwezig>1</Aanwezig><Gelezen>1</Gelezen></Strip><Strip><ID>1552</ID><Nummer>6</Nummer><Titel>De tweekoppige drenkeling</Titel><Aanwezig>1</Aanwezig><Gelezen>1</Gelezen></Strip><Strip><ID>1553</ID><Nummer>7</Nummer><Titel>Allemaal monsters</Titel><Aanwezig>1</Aanwezig><Gelezen>1</Gelezen></Strip><Strip><ID>1554</ID><Nummer>8</Nummer><Titel>Het geheim der diepten</Titel><Aanwezig>1</Aanwezig><Gelezen>1</Gelezen></Strip><Strip><ID>2132</ID><Nummer>9</Nummer><Titel>Het helse labyrinth</Titel><Aanwezig>1</Aanwezig><Gelezen>1</Gelezen></Strip><Strip><ID>3407</ID><Nummer>10</Nummer><Titel>De baby van Buttes-Chaumont</Titel><Aanwezig>0</Aanwezig><Gelezen>0</Gelezen></Strip></Reeks>